[
  {
    "id": "nil-dec12-001",
    "category": "News",
    "featured": true,
    "image": "https://images.unsplash.com/photo-1504711434969-e33886168d5c?w=800&q=80",
    "title": "Ooty shivers amid sharp dip in temperatures, frost blankets Tamil Nadu's Nilgiris",
    "title_ta": "",
    "summary": "Ooty shivers amid sharp dip in temperatures, frost blankets Tamil Nadu's Nilgiris",
    "summary_ta": "",
    "date": "December 12, 2025"
  },
  {
    "id": "nil-apr23-002",
    "category": "News",
    "featured": false,
    "image": "https://images.unsplash.com/photo-1504711434969-e33886168d5c?w=800&q=80",
    "title": "Tamil Nadu election 2026: High voter turnout in Nilgiris",
    "title_ta": "",
    "summary": "Tamil Nadu election 2026: High voter turnout in Nilgiris",
    "summary_ta": "",
    "date": "April 23, 2026"
  },
  {
    "id": "nil-apr24-003",
    "category": "News",
    "featured": false,
    "image": "https://images.unsplash.com/photo-1504711434969-e33886168d5c?w=800&q=80",
    "title": "Ajjoor villagers in Ooty boycott polls over land issues, later vote NOTA to protest official apathy",
    "title_ta": "",
    "summary": "Ajjoor villagers in Ooty boycott polls over land issues, later vote NOTA to protest official apathy",
    "summary_ta": "",
    "date": "April 24, 2026"
  },
  {
    "id": "nil-jul22-004",
    "category": "News",
    "featured": false,
    "image": "https://images.unsplash.com/photo-1504711434969-e33886168d5c?w=800&q=80",
    "title": "Nilgiris Tibetan Refugee Welfare Association Observes His Holiness' 90th Birthday & its Golden Jubil",
    "title_ta": "",
    "summary": "Nilgiris Tibetan Refugee Welfare Association Observes His Holiness' 90th Birthday & its Golden Jubil",
    "summary_ta": "",
    "date": "July 22, 2025"
  },
  {
    "id": "nil-apr29-005",
    "category": "News",
    "featured": false,
    "image": "https://images.unsplash.com/photo-1504711434969-e33886168d5c?w=800&q=80",
    "title": "5,000 acres charred, fresh blaze under control. Why Nilgiris forest fires are more intense this year",
    "title_ta": "",
    "summary": "5,000 acres charred, fresh blaze under control. Why Nilgiris forest fires are more intense this year",
    "summary_ta": "",
    "date": "April 29, 2026"
  },
  {
    "id": "nil-may4-006",
    "category": "News",
    "featured": false,
    "image": "https://images.unsplash.com/photo-1504711434969-e33886168d5c?w=800&q=80",
    "title": "Udhagamandalam election results 2026: BJP's Bhojarajan M with with 48,488 votes",
    "title_ta": "",
    "summary": "Udhagamandalam election results 2026: BJP's Bhojarajan M with with 48,488 votes",
    "summary_ta": "",
    "date": "May 4, 2026"
  }
]
